unpage/__init__.py
unpage/config.py
unpage/mcp.py
unpage/models.py
unpage/sentry.py
unpage/telemetry.py
unpage/utils.py
unpage/warnings.py
unpage/agent/__init__.py
unpage/agent/analysis.py
unpage/agent/app.py
unpage/agent/prompts.py
unpage/agent/scheduler.py
unpage/agent/utils.py
unpage/agent/templates/blank.yaml
unpage/agent/templates/cost-optimization.yaml
unpage/agent/templates/default.yaml
unpage/agent/templates/fix_gha_build_failures.yaml
unpage/agent/templates/handle_critical_disk_space_alerts.yaml
unpage/agent/templates/investigate_azure_error_with_mcp.yaml
unpage/agent/templates/investigate_db_cxn_pool_exhaustion.yaml
unpage/agent/templates/investigate_gcp_cloud_sql_error.yaml
unpage/agent/templates/investigate_gcp_compute_instance_error.yaml
unpage/agent/templates/investigate_k8s_crash_loop_backoff.yaml
unpage/agent/templates/investigate_ssl_connection_failures.yaml
unpage/agent/templates/review_code_with_git_3p_mcp.yaml
unpage/agent/templates/scheduled.yaml
unpage/agent/templates/slack_alert_notifier.yaml
unpage/cli/__init__.py
unpage/cli/_app.py
unpage/cli/configure.py
unpage/cli/version.py
unpage/cli/agent/__init__.py
unpage/cli/agent/_app.py
unpage/cli/agent/actions.py
unpage/cli/agent/create.py
unpage/cli/agent/delete.py
unpage/cli/agent/edit.py
unpage/cli/agent/list.py
unpage/cli/agent/quickstart.py
unpage/cli/agent/route.py
unpage/cli/agent/run.py
unpage/cli/agent/schedule.py
unpage/cli/agent/serve.py
unpage/cli/agent/templates.py
unpage/cli/graph/__init__.py
unpage/cli/graph/_app.py
unpage/cli/graph/_background.py
unpage/cli/graph/build.py
unpage/cli/graph/logs.py
unpage/cli/graph/status.py
unpage/cli/graph/stop.py
unpage/cli/mcp/__init__.py
unpage/cli/mcp/_app.py
unpage/cli/mcp/start.py
unpage/cli/mcp/client/__init__.py
unpage/cli/mcp/client/_app.py
unpage/cli/mcp/client/logs/__init__.py
unpage/cli/mcp/client/logs/app.py
unpage/cli/mcp/client/logs/claude.py
unpage/cli/mcp/tools/__init__.py
unpage/cli/mcp/tools/_app.py
unpage/cli/mcp/tools/call.py
unpage-0.1.0a45.dist-info/METADATA
unpage-0.1.0a45.dist-info/WHEEL
unpage-0.1.0a45.dist-info/entry_points.txt
unpage-0.1.0a45.dist-info/licenses/LICENSE.md
unpage-0.1.0a45.dist-info/RECORD
